lurk-0.1.3.dist-info/DESCRIPTION.rst
lurk-0.1.3.dist-info/METADATA
lurk-0.1.3.dist-info/RECORD
lurk-0.1.3.dist-info/WHEEL
lurk-0.1.3.dist-info/entry_points.txt
lurk-0.1.3.dist-info/metadata.json
lurk-0.1.3.dist-info/top_level.txt
module/__init__.py
