Metadata-Version: 1.1
Name: lurk
Version: 0.1.3
Summary: Extract html from one or multiple urls
Home-page: https://github.com/mateogianolio/lurk
Author: Mateo Gianolio
Author-email: gianoliomateo@gmail.com
License: MIT
Keywords: lurk lurker scrape scraper scraping webscrape crawl crawler crawling
Platform: UNKNOWN
Classifier: Development Status :: 3 - Alpha
Classifier: Intended Audience :: Developers
Classifier: Topic :: Software Development :: Libraries
Classifier: License :: OSI Approved :: MIT License
Classifier: Programming Language :: Python :: 2
Classifier: Programming Language :: Python :: 2.6
Classifier: Programming Language :: Python :: 2.7
Classifier: Programming Language :: Python :: 3
Classifier: Programming Language :: Python :: 3.2
Classifier: Programming Language :: Python :: 3.3
Classifier: Programming Language :: Python :: 3.4
